pydit/__init__.py
pydit/adapters/logging/interfaces/__init__.py
pydit/adapters/logging/interfaces/logger.py
pydit/adapters/logging/std/__init__.py
pydit/adapters/logging/std/logger.py
pydit/core/__init__.py
pydit/core/dependencies.py
pydit/core/register.py
pydit/core/resolver.py
pydit/exceptions/__init__.py
pydit/exceptions/cant_set_dependency_property.py
pydit/exceptions/custom.py
pydit/exceptions/dependency_not_found.py
pydit/exceptions/missing_property_type.py
pydit/factories/logging/__init__.py
pydit/factories/logging/python.py
pydit/factories/logging/type.py
pydit/types/__init__.py
pydit/types/dependency.py
pydit/types/dependency_property.py
pydit/utils/__init__.py
pydit/utils/is_dunder.py
pydit/utils/logging.py
pydit/utils/remove_dunders.py
pydit/utils/remove_private_protected.py
python_pydit-0.2.1.dist-info/LICENSE.txt
python_pydit-0.2.1.dist-info/METADATA
python_pydit-0.2.1.dist-info/WHEEL
python_pydit-0.2.1.dist-info/RECORD
