Metadata-Version: 2.1
Name: python-pydit
Version: 0.2.1
Summary: A python dependency injection lib
Home-page: https://github.com/MrM4rc/pydit
License: bsd3
Keywords: Dependency Injection,Python,DI,SOLID
Author: Marcelo Almeida (MrM4rc)
Author-email: marcelorap345@gmail.com
Requires-Python: >=3.10,<4.0
Classifier: License :: OSI Approved :: BSD License
Classifier: License :: Other/Proprietary License
Classifier: Operating System :: OS Independent
Classifier: Programming Language :: Python :: 3
Classifier: Programming Language :: Python :: 3.10
Classifier: Programming Language :: Python :: 3.11
Classifier: Programming Language :: Python :: 3.12
Classifier: Programming Language :: Python :: 3.13
Project-URL: Repository, https://github.com/MrM4rc/pydit
